silero_vad_mindspore/__init__.py
silero_vad_mindspore/silero_vad_v4.py
silero_vad_mindspore/utils.py
tests/__init__.py
tests/test_silero_vad_v4.py
tests/test_utils.py
silero_vad_mindspore-0.0.1.dist-info/LICENSE
silero_vad_mindspore-0.0.1.dist-info/METADATA
silero_vad_mindspore-0.0.1.dist-info/WHEEL
silero_vad_mindspore-0.0.1.dist-info/top_level.txt
silero_vad_mindspore-0.0.1.dist-info/RECORD
