Metadata-Version: 2.1
Name: silero_vad_mindspore
Version: 0.0.1
Summary: MindSpore version of Silero VAD.
Home-page: https://github.com/lvyufeng/silero_vad_mindspore
Author: Lvyufeng
Author-email: lvyufeng@cqu.edu.cn
License: Apache License 2.0
Keywords: msimilarities,Chinese Text Similarity Calculation Tool,similarity,word2vec
Classifier: Development Status :: 5 - Production/Stable
Classifier: Intended Audience :: Developers
Classifier: Intended Audience :: Education
Classifier: Intended Audience :: Science/Research
Classifier: License :: OSI Approved :: Apache Software License
Classifier: Operating System :: OS Independent
Classifier: Programming Language :: Python :: 3
Classifier: Topic :: Scientific/Engineering :: Artificial Intelligence
Requires-Python: >=3.9.0
License-File: LICENSE
Requires-Dist: mindnlp
